ai_stream_interact/__init__.py
ai_stream_interact/streamer.py
ai_stream_interact/base/__init__.py
ai_stream_interact/base/ai_interact_base.py
ai_stream_interact/models/__init__.py
ai_stream_interact/models/gemini.py
ai_stream_interact/runners/__init__.py
ai_stream_interact/runners/run_ai.py
ai_stream_interact/tts/__init__.py
ai_stream_interact/tts/coqui_ai.py
ai_stream_interact/tts/printout_utils.py
ai_stream_interact/utils/__init__.py
ai_stream_interact/utils/img_utils.py
ai_stream_interact/utils/video.py
ai_stream_interact-0.0.9.dist-info/COPYING
ai_stream_interact-0.0.9.dist-info/METADATA
ai_stream_interact-0.0.9.dist-info/WHEEL
ai_stream_interact-0.0.9.dist-info/entry_points.txt
ai_stream_interact-0.0.9.dist-info/top_level.txt
ai_stream_interact-0.0.9.dist-info/RECORD
